{
  "dataset_name": "philippine_imbalanced",
  "classification_type": "binary",
  "class_balance": "imbalanced",
  "correlation_type": "spearman",
  "correlation_matrix": {
    "macro_accuracy": {
      "macro_accuracy": 1.0,
      "micro_accuracy": 1.0,
      "macro_precision": 0.9949474644491425,
      "micro_precision": 1.0,
      "macro_recall": -0.3443284988270742,
      "micro_recall": 1.0,
      "macro_f1": 0.6153592280892551,
      "micro_f1": 1.0,
      "MSE": -0.7710577321334866,
      "LogLoss": -0.6074263872079788,
      "AUNU": 0.6138710703445074,
      "micro_ROC-AUC": 0.6138710703445074
    },
    "micro_accuracy": {
      "macro_accuracy": 1.0,
      "micro_accuracy": 1.0,
      "macro_precision": 0.9949474644491425,
      "micro_precision": 1.0,
      "macro_recall": -0.3443284988270742,
      "micro_recall": 1.0,
      "macro_f1": 0.6153592280892551,
      "micro_f1": 1.0,
      "MSE": -0.7710577321334866,
      "LogLoss": -0.6074263872079788,
      "AUNU": 0.6138710703445074,
      "micro_ROC-AUC": 0.6138710703445074
    },
    "macro_precision": {
      "macro_accuracy": 0.9949474644491425,
      "micro_accuracy": 0.9949474644491425,
      "macro_precision": 1.0,
      "micro_precision": 0.9949474644491425,
      "macro_recall": -0.27707170717071705,
      "micro_recall": 0.9949474644491425,
      "macro_f1": 0.6562256225622562,
      "micro_f1": 0.9949474644491425,
      "MSE": -0.803948394839484,
      "LogLoss": -0.6514851485148515,
      "AUNU": 0.6583378337833783,
      "micro_ROC-AUC": 0.6583378337833783
    },
    "micro_precision": {
      "macro_accuracy": 1.0,
      "micro_accuracy": 1.0,
      "macro_precision": 0.9949474644491425,
      "micro_precision": 1.0,
      "macro_recall": -0.3443284988270742,
      "micro_recall": 1.0,
      "macro_f1": 0.6153592280892551,
      "micro_f1": 1.0,
      "MSE": -0.7710577321334866,
      "LogLoss": -0.6074263872079788,
      "AUNU": 0.6138710703445074,
      "micro_ROC-AUC": 0.6138710703445074
    },
    "macro_recall": {
      "macro_accuracy": -0.3443284988270742,
      "micro_accuracy": -0.3443284988270742,
      "macro_precision": -0.27707170717071705,
      "micro_precision": -0.3443284988270742,
      "macro_recall": 1.0,
      "micro_recall": -0.3443284988270742,
      "macro_f1": 0.44346834683468345,
      "micro_f1": -0.3443284988270742,
      "MSE": -0.14527452745274527,
      "LogLoss": -0.3473387338733873,
      "AUNU": 0.34001800180018,
      "micro_ROC-AUC": 0.34001800180018
    },
    "micro_recall": {
      "macro_accuracy": 1.0,
      "micro_accuracy": 1.0,
      "macro_precision": 0.9949474644491425,
      "micro_precision": 1.0,
      "macro_recall": -0.3443284988270742,
      "micro_recall": 1.0,
      "macro_f1": 0.6153592280892551,
      "micro_f1": 1.0,
      "MSE": -0.7710577321334866,
      "LogLoss": -0.6074263872079788,
      "AUNU": 0.6138710703445074,
      "micro_ROC-AUC": 0.6138710703445074
    },
    "macro_f1": {
      "macro_accuracy": 0.6153592280892551,
      "micro_accuracy": 0.6153592280892551,
      "macro_precision": 0.6562256225622562,
      "micro_precision": 0.6153592280892551,
      "macro_recall": 0.44346834683468345,
      "micro_recall": 0.6153592280892551,
      "macro_f1": 1.0,
      "micro_f1": 0.6153592280892551,
      "MSE": -0.8454245424542455,
      "LogLoss": -0.8367476747674768,
      "AUNU": 0.8336993699369937,
      "micro_ROC-AUC": 0.8336993699369937
    },
    "micro_f1": {
      "macro_accuracy": 1.0,
      "micro_accuracy": 1.0,
      "macro_precision": 0.9949474644491425,
      "micro_precision": 1.0,
      "macro_recall": -0.3443284988270742,
      "micro_recall": 1.0,
      "macro_f1": 0.6153592280892551,
      "micro_f1": 1.0,
      "MSE": -0.7710577321334866,
      "LogLoss": -0.6074263872079788,
      "AUNU": 0.6138710703445074,
      "micro_ROC-AUC": 0.6138710703445074
    },
    "MSE": {
      "macro_accuracy": -0.7710577321334866,
      "micro_accuracy": -0.7710577321334866,
      "macro_precision": -0.803948394839484,
      "micro_precision": -0.7710577321334866,
      "macro_recall": -0.14527452745274527,
      "micro_recall": -0.7710577321334866,
      "macro_f1": -0.8454245424542455,
      "micro_f1": -0.7710577321334866,
      "MSE": 1.0,
      "LogLoss": 0.9421662166216621,
      "AUNU": -0.945946594659466,
      "micro_ROC-AUC": -0.945946594659466
    },
    "LogLoss": {
      "macro_accuracy": -0.6074263872079788,
      "micro_accuracy": -0.6074263872079788,
      "macro_precision": -0.6514851485148515,
      "micro_precision": -0.6074263872079788,
      "macro_recall": -0.3473387338733873,
      "micro_recall": -0.6074263872079788,
      "macro_f1": -0.8367476747674768,
      "micro_f1": -0.6074263872079788,
      "MSE": 0.9421662166216621,
      "LogLoss": 1.0,
      "AUNU": -0.9983198319831983,
      "micro_ROC-AUC": -0.9983198319831983
    },
    "AUNU": {
      "macro_accuracy": 0.6138710703445074,
      "micro_accuracy": 0.6138710703445074,
      "macro_precision": 0.6583378337833783,
      "micro_precision": 0.6138710703445074,
      "macro_recall": 0.34001800180018,
      "micro_recall": 0.6138710703445074,
      "macro_f1": 0.8336993699369937,
      "micro_f1": 0.6138710703445074,
      "MSE": -0.945946594659466,
      "LogLoss": -0.9983198319831983,
      "AUNU": 1.0,
      "micro_ROC-AUC": 1.0
    },
    "micro_ROC-AUC": {
      "macro_accuracy": 0.6138710703445074,
      "micro_accuracy": 0.6138710703445074,
      "macro_precision": 0.6583378337833783,
      "micro_precision": 0.6138710703445074,
      "macro_recall": 0.34001800180018,
      "micro_recall": 0.6138710703445074,
      "macro_f1": 0.8336993699369937,
      "micro_f1": 0.6138710703445074,
      "MSE": -0.945946594659466,
      "LogLoss": -0.9983198319831983,
      "AUNU": 1.0,
      "micro_ROC-AUC": 1.0
    }
  }
}